termyak/__init__.py
termyak/py.typed
termyak-0.1.0rc1.dist-info/WHEEL
termyak-0.1.0rc1.dist-info/METADATA
termyak-0.1.0rc1.dist-info/RECORD
